{
  "mappings": {
    "stephen/betterpaths/mixin/HoeItemMixin": {
      "Lnet/minecraft/item/Item;useOnBlock(Lnet/minecraft/item/ItemUsageContext;)Lnet/minecraft/util/ActionResult;": "Lnet/minecraft/class_1792;method_7884(Lnet/minecraft/class_1838;)Lnet/minecraft/class_1269;",
      "useOnBlock": "Lnet/minecraft/class_1794;method_7884(Lnet/minecraft/class_1838;)Lnet/minecraft/class_1269;"
    },
    "stephen/betterpaths/mixin/ShovelItemMixin": {
      "Lnet/minecraft/item/Item;useOnBlock(Lnet/minecraft/item/ItemUsageContext;)Lnet/minecraft/util/ActionResult;": "Lnet/minecraft/class_1792;method_7884(Lnet/minecraft/class_1838;)Lnet/minecraft/class_1269;",
      "useOnBlock": "Lnet/minecraft/class_1821;method_7884(Lnet/minecraft/class_1838;)Lnet/minecraft/class_1269;"
    }
  },
  "data": {
    "named:intermediary": {
      "stephen/betterpaths/mixin/HoeItemMixin": {
        "Lnet/minecraft/item/Item;useOnBlock(Lnet/minecraft/item/ItemUsageContext;)Lnet/minecraft/util/ActionResult;": "Lnet/minecraft/class_1792;method_7884(Lnet/minecraft/class_1838;)Lnet/minecraft/class_1269;",
        "useOnBlock": "Lnet/minecraft/class_1794;method_7884(Lnet/minecraft/class_1838;)Lnet/minecraft/class_1269;"
      },
      "stephen/betterpaths/mixin/ShovelItemMixin": {
        "Lnet/minecraft/item/Item;useOnBlock(Lnet/minecraft/item/ItemUsageContext;)Lnet/minecraft/util/ActionResult;": "Lnet/minecraft/class_1792;method_7884(Lnet/minecraft/class_1838;)Lnet/minecraft/class_1269;",
        "useOnBlock": "Lnet/minecraft/class_1821;method_7884(Lnet/minecraft/class_1838;)Lnet/minecraft/class_1269;"
      }
    }
  }
}